setup.py
cameo_claw/__init__.py
cameo_claw/__main__.py
cameo_claw/cameo_claw.py
cameo_claw/cameo_claw_reuse.py
cameo_claw/client.py
cameo_claw/file.py
cameo_claw/functional.py
cameo_claw/istarmap.py
cameo_claw/log.py
cameo_claw/net.py
cameo_claw/ocean.py
cameo_claw/remote.py
cameo_claw/scheduler.py
cameo_claw/streaming.py
cameo_claw/worker.py
cameo_claw/worker_f.py
cameo_claw.egg-info/PKG-INFO
cameo_claw.egg-info/SOURCES.txt
cameo_claw.egg-info/dependency_links.txt
cameo_claw.egg-info/requires.txt
cameo_claw.egg-info/top_level.txt
test/test.py
test/test_client.py
test/test_hourly_mean.py
test/test_with_fastapi.py