Metadata-Version: 2.1
Name: cameo-claw
Version: 1.4.1
Summary: Multiprocessing download, filter, streaming. ⚡️FAST⚡️ remove pandas
Home-page: https://github.com/bohachu/cameo_claw
Author: Bowen Chiu
Author-email: bohachu@gmail.com
License: BSD 2-clause
Platform: UNKNOWN
Classifier: Programming Language :: Python :: 3
